interactive_data_manipulation/__init__.py
interactive_data_manipulation/dataframe.py
interactive_data_manipulation/idm.py
interactive_data_manipulation/summary.py
interactive_data_manipulation-0.0.22.dist-info/LICENSE
interactive_data_manipulation-0.0.22.dist-info/METADATA
interactive_data_manipulation-0.0.22.dist-info/WHEEL
interactive_data_manipulation-0.0.22.dist-info/top_level.txt
interactive_data_manipulation-0.0.22.dist-info/RECORD
