Metadata-Version: 2.1
Name: interactive-data-manipulation
Version: 0.0.22
Summary: A library for Jupyter notebook interactive data manipulations
Home-page: https://github.com/telenovelachuan/interactive_data_manipulation
Author: ChuanSun
Author-email: chuansun.sc@gmail.com
License: UNKNOWN
Platform: UNKNOWN
Classifier: Programming Language :: Python :: 3
Classifier: License :: OSI Approved :: MIT License
Classifier: Operating System :: OS Independent
Requires-Python: >=3.0
